pathogen_embed/__init__.py
pathogen_embed/__main__.py
pathogen_embed/pathogen_embed.py
pathogen_embed-3.1.0.dist-info/LICENSE
pathogen_embed-3.1.0.dist-info/METADATA
pathogen_embed-3.1.0.dist-info/WHEEL
pathogen_embed-3.1.0.dist-info/entry_points.txt
pathogen_embed-3.1.0.dist-info/top_level.txt
pathogen_embed-3.1.0.dist-info/RECORD
