Metadata-Version: 2.1
Name: pathogen-embed
Version: 3.1.0
Summary: Reduced dimension embeddings for pathogen sequences
Home-page: https://github.com/blab/pathogen-embed/
Author: Sravani Nanduri <nandsra@cs.washington.edu> , John Huddleston <huddlej@gmail.com>
Author-email: nandsra@cs.washington.edu
License: MIT License
Project-URL: Documentation, https://blab.github.io/pathogen-embed/
Project-URL: Bug Reports, https://github.com/blab/pathogen-embed/issues
Project-URL: Source Code, https://github.com/blab/pathogen-embed/tree/main
Project-URL: Change Log, https://github.com/blab/pathogen-embed/tree/main/CHANGES.md
Classifier: Operating System :: OS Independent
Classifier: Intended Audience :: Science/Research
Classifier: License :: OSI Approved :: MIT License
Classifier: Programming Language :: Python :: 3
Classifier: Programming Language :: Python :: 3.8
Classifier: Programming Language :: Python :: 3.9
Classifier: Programming Language :: Python :: 3.10
Classifier: Programming Language :: Python :: 3.11
License-File: LICENSE
Requires-Dist: numpy
Requires-Dist: pandas
Requires-Dist: biopython
Requires-Dist: scikit-learn<1.5,>=1.3
Requires-Dist: umap-learn==0.5.*
Requires-Dist: numba<0.59.0
Requires-Dist: matplotlib
Requires-Dist: hdbscan
Provides-Extra: dev
Requires-Dist: cram>=0.7; extra == "dev"
